dynamic-library.pth
dynamic_library/__init__.py
dynamic_library/_hook.py
dynamic_library/_import.py
dynamic_library-0.2.0.dist-info/METADATA
dynamic_library-0.2.0.dist-info/WHEEL
dynamic_library-0.2.0.dist-info/licenses/LICENSE.txt
dynamic_library-0.2.0.dist-info/RECORD
