Metadata-Version: 2.4
Name: dynamic-library
Version: 0.2.0
Summary: Hook to load package-provided dynamic libraries
Project-URL: Documentation, https://github.com/Filipe Laíns/dynamic-library#readme
Project-URL: Issues, https://github.com/Filipe Laíns/dynamic-library/issues
Project-URL: Source, https://github.com/Filipe Laíns/dynamic-library
Author-email: Filipe Laíns <lains@riseup.net>
License-Expression: MIT
License-File: LICENSE.txt
Classifier: Development Status :: 4 - Beta
Classifier: Programming Language :: Python
Classifier: Programming Language :: Python :: 3.9
Classifier: Programming Language :: Python :: 3.10
Classifier: Programming Language :: Python :: 3.11
Classifier: Programming Language :: Python :: 3.12
Classifier: Programming Language :: Python :: Implementation :: CPython
Classifier: Programming Language :: Python :: Implementation :: PyPy
Requires-Python: >=3.9
Provides-Extra: test
Requires-Dist: environment-helpers>=0.2.0; extra == 'test'
Requires-Dist: patchelf; (sys_platform == 'linux') and extra == 'test'
Requires-Dist: pytest; extra == 'test'
Requires-Dist: pytest-cov>=5; extra == 'test'
Requires-Dist: pytest-github-actions-annotate-failures; extra == 'test'
